lacbox/__init__.py
lacbox/io.py
lacbox/postprocess.py
lacbox/vis.py
lacbox/gtsdf/__init__.py
lacbox/gtsdf/gtsdf.py
lacbox/gtsdf/unix_time.py
lacbox/htc/__init__.py
lacbox/htc/htc_contents.py
lacbox/htc/htc_extensions.py
lacbox/htc/htc_file.py
lacbox/htc/os_path.py
lacbox/rotor_design/__init__.py
lacbox/rotor_design/aero_design.py
lacbox/rotor_design/structural_scaling.py
lacbox/rotor_design/utils.py
lacbox/test/__init__.py
lacbox/test/test_aero.py
lacbox/test/test_aero_design_functions.py
lacbox/test/test_io.py
lacbox/test/_data/DTU_10MW_RWT.pwr
lacbox/test/_data/DTU_10MW_RWT_u8000.ind
lacbox/test/_data/DTU_10MW_RWT_u8001.ind
lacbox/test/_data/DTU_10MW_RWT_u8002.ind
lacbox/test/_data/DTU_10MW_RWT_u8003.ind
lacbox/test/_data/DTU_10MW_RWT_u8004.ind
lacbox/test/_data/DTU_10MW_RWT_u8005.ind
lacbox/test/_data/DTU_10MW_RWT_u8006.ind
lacbox/test/_data/dtu_10mw_hawc2s_ctrltune_ctrl_tuning.txt
lacbox/test/_data/dtu_10mw_steady_stats.hdf5
lacbox/test/_data/dtu_10mw_structural.amp
lacbox/test/_data/dtu_10mw_structural.cmb
lacbox/test/_data/dtu_10mw_turb.hdf5
lacbox/test/_data/ideal_planform.dat
lacbox/test/_data/uneven_pc.dat
lacbox/test/_data/dtu_10_mw/DTU_10MW_RWT.htc
lacbox/test/_data/dtu_10_mw/data/DTU_10MW_RWT_Blade_st.dat
lacbox/test/_data/dtu_10_mw/data/DTU_10MW_RWT_Hub_st.dat
lacbox/test/_data/dtu_10_mw/data/DTU_10MW_RWT_Shaft_st.dat
lacbox/test/_data/dtu_10_mw/data/DTU_10MW_RWT_Tower_st.dat
lacbox/test/_data/dtu_10_mw/data/DTU_10MW_RWT_Towertop_st.dat
lacbox/test/_data/dtu_10_mw/data/DTU_10MW_RWT_ae.dat
lacbox/test/_data/dtu_10_mw/data/DTU_10MW_RWT_pc.dat
lacbox/test/_data/dtu_10_mw/data/operation_data.dat
lacbox-0.4.0.dist-info/METADATA
lacbox-0.4.0.dist-info/WHEEL
lacbox-0.4.0.dist-info/licenses/LICENSE
lacbox-0.4.0.dist-info/RECORD
