Metadata-Version: 2.4
Name: lacbox
Version: 0.4.0
Summary: Toolbox for LAC course at DTU Wind Energy
Project-URL: Documentation, https://lac-course.pages.windenergy.dtu.dk/lacbox/
Project-URL: Repository, https://gitlab.windenergy.dtu.dk/lac-course/lacbox
Project-URL: Bug Tracker, https://gitlab.windenergy.dtu.dk/lac-course/lacbox/-/issues
Author-email: DTU Wind Energy <rink@dtu.dk>
Maintainer-email: Jenni Rinker <rink@dtu.dk>, Kenneth Lønbæk <kenloen@dtu.dk>
License: MIT License
License-File: LICENSE
Requires-Python: >=3.9
Requires-Dist: h5py
Requires-Dist: jupyter
Requires-Dist: matplotlib
Requires-Dist: numpy
Requires-Dist: pandas
Requires-Dist: scipy
Requires-Dist: tables
Provides-Extra: dev
Requires-Dist: build; extra == 'dev'
Requires-Dist: nbsphinx; extra == 'dev'
Requires-Dist: pytest; extra == 'dev'
Requires-Dist: sphinx; extra == 'dev'
Requires-Dist: sphinx-rtd-theme; extra == 'dev'
Requires-Dist: twine; extra == 'dev'
